tensor_walks/__init__.py
tensor_walks/core.py
tensor_walks/impl_np.py
tensor_walks/impl_torch.py
tensor_walks-0.0.7.dist-info/METADATA
tensor_walks-0.0.7.dist-info/WHEEL
tensor_walks-0.0.7.dist-info/top_level.txt
tensor_walks-0.0.7.dist-info/RECORD
